{
    "id": "odhf",
    "style": "mapbox://styles/deil-leid/ck80mmo1r0xnw1ippsaxqay1t",
    "layers": [{
            "id": "odhf"
        }
    ],
    "title": {
        "en": "Open database of health facilities",
        "fr": "Base de données ouvertes des établissement de santé"
    },
    "description": null,
    "legend": [{
            "color": [228,26,28],
            "label": {
                "en": "Residential care",
                "fr": "Soins résidentiels"
            },
            "value": ["==", ["get", "Type"], "1"]
        }, {
            "color": [55,126,184],
            "label": {
                "en": "Outpatient Health Services",
                "fr": "Services de santé ambulatoire"
            },
            "value": ["==", ["get", "Type"], "2"]
        }, {
            "color": [152,78,163],
            "label": {
                "en": "Acute care hospital",
                "fr": "Hôpital de soins intensifs"
            },
            "value": ["==", ["get", "Type"], "4"]
        }, {
            "color": [77,175,74],
            "label": {
                "en": "Residential care and <br>Outpatient Health Services",
                "fr": "Soins résidentiels et <br>Services de santé ambulatoire"
            },
            "value": ["==", ["get", "Type"], "3"]
        }, {
            "color": [255,127,0],
            "label": {
                "en": "Acute care hospital and<br> Residential care",
                "fr": "Hôpital de soins intensifs et<br> Soins résidentiels"
            },
            "value": ["==", ["get", "Type"], "5"]
        }, {
            "color": [255,255,51],
            "label": {
                "en": "Acute care hospital and<br> Outpatient Health Services",
                "fr": "Hôpital de soins intensifs et<br> Services de santé ambulatoire"
            },
            "value": ["==", ["get", "Type"], "6"]
        }, {
            "color": [166,86,40],
            "label": {
                "en": "All three types",
                "fr": "Les trois types"
            },
            "value": ["==", ["get", "Type"], "7"]
        }, {
            "label": {
                "en": "Unknown",
                "fr": "Inconnu"
            },
            "color": [175,175,175]
        }
    ],
    "fields": [{
            "id": "index",
            "label": {
                "en": "Index",
                "fr": "Indice"
            }
        },{
            "id": "hospital_type",
            "label": {
                "en": "Hospital type",
                "fr": "Type d'hôpital"
            }
        }, {
            "id": "hospital_name",
            "label": {
                "en": "Hospital name",
                "fr": "Nom de l'hôpital"
            }
        }, {
            "id": "full_address",
            "label": {
                "en": "Address",
                "fr": "Addresse"
            }
        }, {
            "id": "latitude",
            "label": {
                "en": "Latitude",
                "fr": "Latitude"
            }
        }, {
            "id": "longitude",
            "label": {
                "en": "Longitude",
                "fr": "Longitude"
            }
        }
    ]


}
